{"working_dir":null,"default_chunk_options":{"echo":true},"chunk_definitions":[{"row":23,"row_count":1,"visible":true,"expansion_state":0,"options":{"engine":"r","label":"setup","include":false},"document_id":"C0356C00","chunk_id":"csetup_chunk","chunk_label":"setup"},{"row":48,"row_count":1,"visible":true,"expansion_state":0,"options":{"engine":"r","label":"import data"},"document_id":"C0356C00","chunk_id":"c39dz95nr4ldl","chunk_label":"import data"},{"row":80,"row_count":1,"visible":true,"expansion_state":0,"options":{},"document_id":"C0356C00","chunk_id":"cqbkqvhmkqtjc","chunk_label":"data filtering IL6 vs ctrl"},{"row":111,"row_count":1,"visible":true,"expansion_state":0,"options":{},"document_id":"C0356C00","chunk_id":"c9h2q3xlqj7lu","chunk_label":"DEXSeq Analysis"},{"row":137,"row_count":1,"visible":true,"expansion_state":0,"options":{},"document_id":"C0356C00","chunk_id":"ci3qvbem21rfn","chunk_label":"stage-wise testing with stageR"},{"row":167,"row_count":1,"visible":true,"expansion_state":0,"options":{},"document_id":"C0356C00","chunk_id":"clbxi4nrvt8s8","chunk_label":"pull out results and export"}],"doc_write_time":1753811079}